airbyte_cdk/__init__.py
airbyte_cdk/config_observation.py
airbyte_cdk/connector.py
airbyte_cdk/entrypoint.py
airbyte_cdk/exception_handler.py
airbyte_cdk/logger.py
airbyte_cdk/py.typed
airbyte_cdk/connector_builder/__init__.py
airbyte_cdk/connector_builder/connector_builder_handler.py
airbyte_cdk/connector_builder/main.py
airbyte_cdk/connector_builder/message_grouper.py
airbyte_cdk/connector_builder/models.py
airbyte_cdk/destinations/__init__.py
airbyte_cdk/destinations/destination.py
airbyte_cdk/destinations/vector_db_based/__init__.py
airbyte_cdk/destinations/vector_db_based/config.py
airbyte_cdk/destinations/vector_db_based/document_processor.py
airbyte_cdk/destinations/vector_db_based/embedder.py
airbyte_cdk/destinations/vector_db_based/indexer.py
airbyte_cdk/destinations/vector_db_based/test_utils.py
airbyte_cdk/destinations/vector_db_based/utils.py
airbyte_cdk/destinations/vector_db_based/writer.py
airbyte_cdk/models/__init__.py
airbyte_cdk/models/airbyte_protocol.py
airbyte_cdk/models/well_known_types.py
airbyte_cdk/sources/__init__.py
airbyte_cdk/sources/abstract_source.py
airbyte_cdk/sources/config.py
airbyte_cdk/sources/connector_state_manager.py
airbyte_cdk/sources/http_config.py
airbyte_cdk/sources/http_logger.py
airbyte_cdk/sources/source.py
airbyte_cdk/sources/concurrent_source/__init__.py
airbyte_cdk/sources/concurrent_source/concurrent_read_processor.py
airbyte_cdk/sources/concurrent_source/concurrent_source.py
airbyte_cdk/sources/concurrent_source/concurrent_source_adapter.py
airbyte_cdk/sources/concurrent_source/partition_generation_completed_sentinel.py
airbyte_cdk/sources/concurrent_source/thread_pool_manager.py
airbyte_cdk/sources/declarative/__init__.py
airbyte_cdk/sources/declarative/create_partial.py
airbyte_cdk/sources/declarative/declarative_component_schema.yaml
airbyte_cdk/sources/declarative/declarative_source.py
airbyte_cdk/sources/declarative/declarative_stream.py
airbyte_cdk/sources/declarative/exceptions.py
lamatic_airbyte_cdk-0.1.0.dist-info/LICENSE.txt
lamatic_airbyte_cdk-0.1.0.dist-info/METADATA
lamatic_airbyte_cdk-0.1.0.dist-info/WHEEL
lamatic_airbyte_cdk-0.1.0.dist-info/top_level.txt
lamatic_airbyte_cdk-0.1.0.dist-info/RECORD
