Metadata-Version: 2.1
Name: lamatic-airbyte-cdk
Version: 0.1.0
Summary: A framework for writing Airbyte Connectors.
Home-page: https://github.com/airbytehq/airbyte
Author: Airbyte
Author-email: contact@airbyte.io
License: MIT
Project-URL: Documentation, https://docs.airbyte.io/
Project-URL: Source, https://github.com/airbytehq/airbyte
Project-URL: Tracker, https://github.com/airbytehq/airbyte/issues
Keywords: airbyte connector-development-kit cdk
Classifier: Development Status :: 3 - Alpha
Classifier: Intended Audience :: Developers
Classifier: Topic :: Scientific/Engineering
Classifier: Topic :: Software Development :: Libraries :: Python Modules
Classifier: License :: OSI Approved :: MIT License
Classifier: Programming Language :: Python :: 3.8
Requires-Python: >=3.8
License-File: LICENSE.txt
Requires-Dist: airbyte-protocol-models ==0.5.1
Requires-Dist: backoff
Requires-Dist: dpath ~=2.0.1
Requires-Dist: isodate ~=0.6.1
Requires-Dist: jsonschema ~=3.2.0
Requires-Dist: jsonref ~=0.2
Requires-Dist: pendulum <3.0.0
Requires-Dist: genson ==1.2.2
Requires-Dist: pydantic <2.0.0,>=1.10.8
Requires-Dist: pyrate-limiter ~=3.1.0
Requires-Dist: python-dateutil
Requires-Dist: PyYAML >=6.0.1
Requires-Dist: requests
Requires-Dist: requests-cache
Requires-Dist: Deprecated ~=1.2
Requires-Dist: Jinja2 ~=3.1.2
Requires-Dist: cachetools
Requires-Dist: wcmatch ==8.4
Provides-Extra: dev
Requires-Dist: avro ~=1.11.2 ; extra == 'dev'
Requires-Dist: fastavro ~=1.8.0 ; extra == 'dev'
Requires-Dist: freezegun ; extra == 'dev'
Requires-Dist: mypy ; extra == 'dev'
Requires-Dist: pytest ; extra == 'dev'
Requires-Dist: pytest-cov ; extra == 'dev'
Requires-Dist: pytest-mock ; extra == 'dev'
Requires-Dist: requests-mock ; extra == 'dev'
Requires-Dist: pytest-httpserver ; extra == 'dev'
Requires-Dist: pandas ==2.0.3 ; extra == 'dev'
Requires-Dist: pyarrow ~=15.0.0 ; extra == 'dev'
Requires-Dist: langchain ==0.0.271 ; extra == 'dev'
Requires-Dist: openai[embeddings] ==0.27.9 ; extra == 'dev'
Requires-Dist: cohere ==4.21 ; extra == 'dev'
Requires-Dist: tiktoken ==0.4.0 ; extra == 'dev'
Requires-Dist: unstructured ==0.10.27 ; extra == 'dev'
Requires-Dist: unstructured[docx,pptx] ==0.10.27 ; extra == 'dev'
Requires-Dist: pdf2image ==1.16.3 ; extra == 'dev'
Requires-Dist: pdfminer.six ==20221105 ; extra == 'dev'
Requires-Dist: unstructured.pytesseract >=0.3.12 ; extra == 'dev'
Requires-Dist: pytesseract ==0.3.10 ; extra == 'dev'
Requires-Dist: markdown ; extra == 'dev'
Provides-Extra: file-based
Requires-Dist: avro ~=1.11.2 ; extra == 'file-based'
Requires-Dist: fastavro ~=1.8.0 ; extra == 'file-based'
Requires-Dist: pyarrow ~=15.0.0 ; extra == 'file-based'
Requires-Dist: unstructured ==0.10.27 ; extra == 'file-based'
Requires-Dist: unstructured[docx,pptx] ==0.10.27 ; extra == 'file-based'
Requires-Dist: pdf2image ==1.16.3 ; extra == 'file-based'
Requires-Dist: pdfminer.six ==20221105 ; extra == 'file-based'
Requires-Dist: unstructured.pytesseract >=0.3.12 ; extra == 'file-based'
Requires-Dist: pytesseract ==0.3.10 ; extra == 'file-based'
Requires-Dist: markdown ; extra == 'file-based'
Provides-Extra: sphinx-docs
Requires-Dist: Sphinx ~=4.2 ; extra == 'sphinx-docs'
Requires-Dist: sphinx-rtd-theme ~=1.0 ; extra == 'sphinx-docs'
Provides-Extra: vector-db-based
Requires-Dist: langchain ==0.0.271 ; extra == 'vector-db-based'
Requires-Dist: openai[embeddings] ==0.27.9 ; extra == 'vector-db-based'
Requires-Dist: cohere ==4.21 ; extra == 'vector-db-based'
Requires-Dist: tiktoken ==0.4.0 ; extra == 'vector-db-based'
